qjob/__init__.py
qjob/_version.py
qjob/cli.py
qjob-0.5.4.dist-info/LICENSE
qjob-0.5.4.dist-info/METADATA
qjob-0.5.4.dist-info/WHEEL
qjob-0.5.4.dist-info/top_level.txt
qjob-0.5.4.dist-info/RECORD
